storyteller/__init__.py
storyteller_ai-0.0.1.dist-info/METADATA
storyteller_ai-0.0.1.dist-info/WHEEL
storyteller_ai-0.0.1.dist-info/top_level.txt
storyteller_ai-0.0.1.dist-info/RECORD
